{
    "pages": [
        {
            "path": "pages/login/form",
            "style": {
                "navigationBarTitleText": "登录"
            }
        },
        {
            "path": "pages/register/form",
            "style": {
                "navigationBarTitleText": "注册"
            }
        },
        {
            "path": "pages/clubs/list",
            "style": {
                "navigationBarTitleText": "社团列表"
            }
        },
        {
            "path": "pages/clubs/detail",
            "style": {
                "navigationBarTitleText": "社团详情"
            }
        },
        {
            "path": "pages/clubs/home",
            "style": {
                "navigationBarTitleText": "社团主页"
            }
        },
        {
            "path": "pages/activities/list",
            "style": {
                "navigationBarTitleText": "我的社团"
            }
        },
        {
            "path": "pages/activities/detail",
            "style": {
                "navigationBarTitleText": "活动详情"
            }
        },
        {
            "path": "pages/announcements/list",
            "style": {
                "navigationBarTitleText": "公告"
            }
        },
        {
            "path": "pages/clubs/attendance",
            "style": {
                "navigationBarTitleText": "打卡记录"
            }
        },
        {
            "path": "pages/clubs/achievements",
            "style": {
                "navigationBarTitleText": "成果展示"
            }
        },
        {
            "path": "pages/clubs/members",
            "style": {
                "navigationBarTitleText": "成员列表"
            }
        },
        {
            "path": "pages/mine/memberships",
            "style": {
                "navigationBarTitleText": "我的"
            }
        },
        {
            "path": "pages/mine/edit",
            "style": {
                "navigationBarTitleText": "编辑资料"
            }
        }
    ],
    "globalStyle": {
        "navigationBarTextStyle": "black",
        "navigationBarTitleText": "社团管理",
        "navigationBarBackgroundColor": "#F8F8F8",
        "backgroundColor": "#F8F8F8"
    },
    "tabBar": {
        "color": "#333",
        "selectedColor": "#007AFF",
        "backgroundColor": "#FFFFFF",
        "list": [
            {
                "pagePath": "pages/clubs/list",
                "text": "社团",
                "iconPath": "static/home.png",
                "selectedIconPath": "static/home_selected.png"
            },
            {
                "pagePath": "pages/activities/list",
                "text": "我的社团",
                "iconPath": "static/club.png",
                "selectedIconPath": "static/club_selected.png"
            },
            {
                "pagePath": "pages/announcements/list",
                "text": "公告",
                "iconPath": "static/announcement.png",
                "selectedIconPath": "static/announcement_selected.png"
            },
            {
                "pagePath": "pages/mine/memberships",
                "text": "我的",
                "iconPath": "static/profile.png",
                "selectedIconPath": "static/profile_selected.png"
            }
        ]
    },
    "uniIdRouter": {}
}
